DrissionPagePro/__init__.py
DrissionPagePro/__init__.pyi
DrissionPagePro/common.py
DrissionPagePro/errors.py
DrissionPagePro/items.py
DrissionPagePro/version.py
DrissionPagePro-4.1.0.17.dist-info/LICENSE
DrissionPagePro-4.1.0.17.dist-info/METADATA
DrissionPagePro-4.1.0.17.dist-info/WHEEL
DrissionPagePro-4.1.0.17.dist-info/entry_points.txt
DrissionPagePro-4.1.0.17.dist-info/top_level.txt
DrissionPagePro-4.1.0.17.dist-info/RECORD
